oss_metrics_kit/__init__.py
ossmk/__init__.py
ossmk/py.typed
ossmk/cli/__init__.py
ossmk/config/__init__.py
ossmk/core/models/__init__.py
ossmk/core/rules/__init__.py
ossmk/core/rules/llm.py
ossmk/core/services/__init__.py
ossmk/core/services/analyze.py
ossmk/core/services/score.py
ossmk/exporters/__init__.py
ossmk/exporters/json.py
ossmk/exporters/parquet.py
ossmk/exporters/stdout.py
ossmk/metrics/__init__.py
ossmk/normalization/__init__.py
ossmk/providers/__init__.py
ossmk/providers/github/__init__.py
ossmk/providers/github/client.py
ossmk/security/fastapi.py
ossmk/security/ratelimit.py
ossmk/security/ratelimit_redis.py
ossmk/storage/__init__.py
ossmk/storage/base.py
ossmk/storage/memory.py
ossmk/storage/postgres.py
ossmk/storage/sqlite.py
ossmk/utils/__init__.py
oss_metrics_kit-0.1.1.dist-info/METADATA
oss_metrics_kit-0.1.1.dist-info/WHEEL
oss_metrics_kit-0.1.1.dist-info/entry_points.txt
oss_metrics_kit-0.1.1.dist-info/licenses/LICENSE
oss_metrics_kit-0.1.1.dist-info/RECORD
