Metadata-Version: 2.4
Name: oss-metrics-kit
Version: 0.1.1
Summary: Unified toolkit to fetch, normalize, score, and export OSS contribution metrics.
Project-URL: Homepage, https://github.com/refactoring-my-path/oss-metrics-kit
Project-URL: Repository, https://github.com/refactoring-my-path/oss-metrics-kit
Project-URL: Issues, https://github.com/refactoring-my-path/oss-metrics-kit/issues
Project-URL: Documentation, https://github.com/refactoring-my-path/oss-metrics-kit/tree/main/docs
Author: refactoring-my-path
License: Apache-2.0
License-File: LICENSE
Keywords: cli,github,metrics,oss,parquet,scoring
Classifier: License :: OSI Approved :: Apache Software License
Classifier: Operating System :: OS Independent
Classifier: Programming Language :: Python :: 3
Classifier: Programming Language :: Python :: 3 :: Only
Classifier: Typing :: Typed
Requires-Python: >=3.11
Requires-Dist: httpx>=0.27
Requires-Dist: pydantic>=2
Requires-Dist: python-dateutil>=2.8.2
Requires-Dist: rich>=13
Requires-Dist: structlog>=24.1
Requires-Dist: tenacity>=8.2
Requires-Dist: typer>=0.12
Provides-Extra: all
Requires-Dist: duckdb>=1.0; extra == 'all'
Requires-Dist: pyarrow>=15; extra == 'all'
Provides-Extra: exporters-parquet
Requires-Dist: pyarrow>=15; extra == 'exporters-parquet'
Provides-Extra: exporters-postgres
Requires-Dist: psycopg[binary]>=3.2; extra == 'exporters-postgres'
Provides-Extra: github-app
Requires-Dist: pyjwt[crypto]>=2.9; extra == 'github-app'
Provides-Extra: llm-anthropic
Requires-Dist: anthropic>=0.34; extra == 'llm-anthropic'
Provides-Extra: llm-openai
Requires-Dist: openai>=1.40; extra == 'llm-openai'
Provides-Extra: metrics
Requires-Dist: opentelemetry-api>=1.24; extra == 'metrics'
Requires-Dist: prometheus-client>=0.20; extra == 'metrics'
Provides-Extra: redis
Requires-Dist: redis>=5; extra == 'redis'
Provides-Extra: sentry
Requires-Dist: sentry-sdk>=2.13; extra == 'sentry'
Provides-Extra: storage-duckdb
Requires-Dist: duckdb>=1.0; extra == 'storage-duckdb'
Requires-Dist: pyarrow>=15; extra == 'storage-duckdb'
